bitcoin_qr_tools/__init__.py
bitcoin_qr_tools/bbqr/__init__.py
bitcoin_qr_tools/bbqr/cli.py
bitcoin_qr_tools/bbqr/consts.py
bitcoin_qr_tools/bbqr/join.py
bitcoin_qr_tools/bbqr/split.py
bitcoin_qr_tools/bbqr/tables.py
bitcoin_qr_tools/bbqr/utils.py
bitcoin_qr_tools/bbqr/version.py
bitcoin_qr_tools/converter_xpub.py
bitcoin_qr_tools/cv2camera.py
bitcoin_qr_tools/data.py
bitcoin_qr_tools/gui/__init__.py
bitcoin_qr_tools/gui/bitcoin_video_widget.py
bitcoin_qr_tools/gui/icons/zoom.png
bitcoin_qr_tools/gui/qr_widgets.py
bitcoin_qr_tools/gui/video_widget.py
bitcoin_qr_tools/i18n.py
bitcoin_qr_tools/multipath_descriptor.py
bitcoin_qr_tools/qr_generator.py
bitcoin_qr_tools/rtsp_camera.py
bitcoin_qr_tools/screen_camera.py
bitcoin_qr_tools/sign_message_request.py
bitcoin_qr_tools/signer_info.py
bitcoin_qr_tools/unified_decoder.py
bitcoin_qr_tools/unified_encoder.py
bitcoin_qr_tools/ur/LICENSE
bitcoin_qr_tools/ur/__init__.py
bitcoin_qr_tools/ur/bytewords.py
bitcoin_qr_tools/ur/cbor_lite.py
bitcoin_qr_tools/ur/constants.py
bitcoin_qr_tools/ur/crc32.py
bitcoin_qr_tools/ur/fountain_decoder.py
bitcoin_qr_tools/ur/fountain_encoder.py
bitcoin_qr_tools/ur/fountain_utils.py
bitcoin_qr_tools/ur/random_sampler.py
bitcoin_qr_tools/ur/ur.py
bitcoin_qr_tools/ur/ur_decoder.py
bitcoin_qr_tools/ur/ur_encoder.py
bitcoin_qr_tools/ur/utils.py
bitcoin_qr_tools/ur/xoshiro256.py
bitcoin_qr_tools/ur_tools.py
bitcoin_qr_tools/urtypes/LICENSE.md
bitcoin_qr_tools/urtypes/README.md
bitcoin_qr_tools/urtypes/__init__.py
bitcoin_qr_tools/urtypes/bytes.py
bitcoin_qr_tools/urtypes/cbor/COPYING
bitcoin_qr_tools/urtypes/cbor/__init__.py
bitcoin_qr_tools/urtypes/cbor/data.py
bitcoin_qr_tools/urtypes/cbor/decoder.py
bitcoin_qr_tools/urtypes/cbor/encoder.py
bitcoin_qr_tools/urtypes/crypto/__init__.py
bitcoin_qr_tools/urtypes/crypto/account.py
bitcoin_qr_tools/urtypes/crypto/bip39.py
bitcoin_qr_tools/urtypes/crypto/coin_info.py
bitcoin_qr_tools/urtypes/crypto/ec_key.py
bitcoin_qr_tools/urtypes/crypto/hd_key.py
bitcoin_qr_tools-1.2.0.dist-info/LICENSE
bitcoin_qr_tools-1.2.0.dist-info/METADATA
bitcoin_qr_tools-1.2.0.dist-info/WHEEL
bitcoin_qr_tools-1.2.0.dist-info/RECORD
