Metadata-Version: 2.1
Name: bitcoin-qr-tools
Version: 1.2.0
Summary: Python bitcoin qr reader and generator
Home-page: https://github.com/andreasgriffin/bitcoin-qrreader
License: GPL-3.0
Author: andreasgriffin
Author-email: andreasgriffin@proton.me
Requires-Python: >=3.9,<3.13
Classifier: License :: OSI Approved :: GNU General Public License v3 (GPLv3)
Classifier: Programming Language :: Python :: 3
Classifier: Programming Language :: Python :: 3.9
Classifier: Programming Language :: Python :: 3.10
Classifier: Programming Language :: Python :: 3.11
Classifier: Programming Language :: Python :: 3.12
Requires-Dist: base58 (>=2.1.1,<3.0.0)
Requires-Dist: bdkpython (>=0.32.0,<0.33.0)
Requires-Dist: hwi (>=3.0.0,<4.0.0)
Requires-Dist: mss (>=9.0.1,<10.0.0)
Requires-Dist: numpy (>=2.0.1,<3.0.0)
Requires-Dist: opencv-python-headless (>=4.10.0.84,<5.0.0.0)
Requires-Dist: pillow (>=10.4.0,<11.0.0)
Requires-Dist: pygame (>=2.6.1,<3.0.0)
Requires-Dist: pyqrcode (>=1.2.1,<2.0.0)
Requires-Dist: pyqt6 (>=6.7.0,<7.0.0)
Requires-Dist: pyzbar (>=0.1.9,<0.2.0)
Requires-Dist: segno (==1.6.1)
